[
	{
		"ID": "1",
		"LanguageName1": "English",
		"LanguageName2": "German",
		"LanguageName3": "Italian",
		"LanguageName4": "Norwegian",
		"LanguageName5": "undef",
		"LanguageName6": "undef",
		"LanguageName7": "undef",
		"LanguageName8": "undef",
		"LanguageName9": "undef",
		"LanguageName10": "undef",
		"FieldTermLabel": "Term",
		"FieldTermExtraALabel": "Info",
		"FieldTermExtraBLabel": "Abb",
		"FieldConferenceInfoLabel": "BoothInfo",
		"FieldConferenceGlossaryLabel": "Source",
		"DatabaseVersion": "5",
		"DatabaseCreation": "|½<´\\¥nEÚü",
		"DatabaseUser": "testUser",
		"Activation": "dsds"
	}
]